tigershark3/__init__.py
tigershark3/__main__.py
tigershark3/tools/__init__.py
tigershark3/tools/xml_extract.py
tigershark3/x12/__init__.py
tigershark3/x12/annotations.py
tigershark3/x12/base.py
tigershark3/x12/common.py
tigershark3/x12/msg_270_4010_X092_A1.py
tigershark3/x12/msg_271_4010_X092_A1.py
tigershark3/x12/msg_276_4010_X093_A1.py
tigershark3/x12/msg_277U_4010_X070.py
tigershark3/x12/msg_277_4010_X093_A1.py
tigershark3/x12/msg_277_5010_X212.py
tigershark3/x12/msg_277_5010_X214.py
tigershark3/x12/msg_278_4010_X094_27_A1.py
tigershark3/x12/msg_278_4010_X094_A1.py
tigershark3/x12/msg_820_4010_X061_A1.py
tigershark3/x12/msg_820_5010_X218.py
tigershark3/x12/msg_820_5010_X218_v2.py
tigershark3/x12/msg_830_4010_PS.py
tigershark3/x12/msg_834_4010_X095_A1.py
tigershark3/x12/msg_834_5010_X220_A1.py
tigershark3/x12/msg_834_5010_X220_A1_v2.py
tigershark3/x12/msg_835_4010_X091_A1.py
tigershark3/x12/msg_835_5010_X221_A1.py
tigershark3/x12/msg_835_5010_X221_A1_v2.py
tigershark3/x12/msg_837Q3_I_5010_X223_A1.py
tigershark3/x12/msg_837Q3_I_5010_X223_A1_v2.py
tigershark3/x12/msg_837_4010_X096_A1.py
tigershark3/x12/msg_837_4010_X097_A1.py
tigershark3/x12/msg_837_4010_X098_A1.py
tigershark3/x12/msg_837_5010_X222_A1.py
tigershark3/x12/msg_841_4010_XXXC.py
tigershark3/x12/msg_997_4010.py
tigershark3/x12/msg_999_5010.py
tigershark3/x12/msg_999_5010X231_A1.py
tigershark3/x12/msg_x12_control_00401.py
tigershark3/x12/msg_x12_control_00501.py
TigerShark3-3.0.dist-info/LICENSE
TigerShark3-3.0.dist-info/METADATA
TigerShark3-3.0.dist-info/WHEEL
TigerShark3-3.0.dist-info/entry_points.txt
TigerShark3-3.0.dist-info/top_level.txt
TigerShark3-3.0.dist-info/RECORD
