Metadata-Version: 2.1
Name: TigerShark3
Version: 3.0
Summary: TigerShark3: An X12/EDI file parser
Author-email: Steven Buss <steven.buss@gmail.com>, Steven Lott <slott56@email.com>
Classifier: Development Status :: 3 - Alpha
Classifier: Intended Audience :: Developers
Classifier: Intended Audience :: Healthcare Industry
Classifier: License :: OSI Approved :: BSD License
Classifier: Operating System :: OS Independent
Classifier: Programming Language :: Python :: 3 :: Only
Classifier: Programming Language :: Python :: 3.11
Classifier: Topic :: Text Processing
Classifier: Topic :: File Formats
Classifier: Topic :: Office/Business
Classifier: Typing :: Typed
Requires-Python: >=3.11
License-File: LICENSE
Provides-Extra: dev
Requires-Dist: sphinx (==5.0.2) ; extra == 'dev'
Requires-Dist: sphinxcontrib-plantuml (==0.25) ; extra == 'dev'
Requires-Dist: pip-tools (==6.13.0) ; extra == 'dev'
Provides-Extra: test
Requires-Dist: pytest (==7.3.1) ; extra == 'test'
Requires-Dist: pytest-cov (==4.0.0) ; extra == 'test'
Requires-Dist: tox (==4.5.1) ; extra == 'test'
Requires-Dist: mypy (==1.3.0) ; extra == 'test'
Requires-Dist: behave (==1.2.6) ; extra == 'test'
